basic_calculator_pkg-0.1.0.dist-info/licenses/LICENSE
calculator/__init__.py
calculator/operation.py
basic_calculator_pkg-0.1.0.dist-info/METADATA
basic_calculator_pkg-0.1.0.dist-info/WHEEL
basic_calculator_pkg-0.1.0.dist-info/top_level.txt
basic_calculator_pkg-0.1.0.dist-info/RECORD
